up_symk-1.3.1.data/purelib/up_symk/__init__.py
up_symk-1.3.1.data/purelib/up_symk/osp_pddl_writer.py
up_symk-1.3.1.data/purelib/up_symk/symk.py
up_symk-1.3.1.data/purelib/up_symk/symk_base.py
up_symk-1.3.1.data/purelib/up_symk/symk/LICENSE.md
up_symk-1.3.1.data/purelib/up_symk/symk/README.md
up_symk-1.3.1.data/purelib/up_symk/symk/fast-downward.py
up_symk-1.3.1.data/purelib/up_symk/symk/builds/release/bin/downward
up_symk-1.3.1.data/purelib/up_symk/symk/builds/release/bin/preprocess
up_symk-1.3.1.data/purelib/up_symk/symk/builds/release/bin/translate/axiom_rules.py
up_symk-1.3.1.data/purelib/up_symk/symk/builds/release/bin/translate/build_model.py
up_symk-1.3.1.data/purelib/up_symk/symk/builds/release/bin/translate/constraints.py
up_symk-1.3.1.data/purelib/up_symk/symk/builds/release/bin/translate/fact_groups.py
up_symk-1.3.1.data/purelib/up_symk/symk/builds/release/bin/translate/graph.py
up_symk-1.3.1.data/purelib/up_symk/symk/builds/release/bin/translate/greedy_join.py
up_symk-1.3.1.data/purelib/up_symk/symk/builds/release/bin/translate/instantiate.py
up_symk-1.3.1.data/purelib/up_symk/symk/builds/release/bin/translate/invariant_finder.py
up_symk-1.3.1.data/purelib/up_symk/symk/builds/release/bin/translate/invariants.py
up_symk-1.3.1.data/purelib/up_symk/symk/builds/release/bin/translate/normalize.py
up_symk-1.3.1.data/purelib/up_symk/symk/builds/release/bin/translate/options.py
up_symk-1.3.1.data/purelib/up_symk/symk/builds/release/bin/translate/pddl_to_prolog.py
up_symk-1.3.1.data/purelib/up_symk/symk/builds/release/bin/translate/sas_tasks.py
up_symk-1.3.1.data/purelib/up_symk/symk/builds/release/bin/translate/sccs.py
up_symk-1.3.1.data/purelib/up_symk/symk/builds/release/bin/translate/simplify.py
up_symk-1.3.1.data/purelib/up_symk/symk/builds/release/bin/translate/split_rules.py
up_symk-1.3.1.data/purelib/up_symk/symk/builds/release/bin/translate/timers.py
up_symk-1.3.1.data/purelib/up_symk/symk/builds/release/bin/translate/tools.py
up_symk-1.3.1.dist-info/LICENSE.md
up_symk-1.3.1.dist-info/METADATA
up_symk-1.3.1.dist-info/WHEEL
up_symk-1.3.1.dist-info/top_level.txt
up_symk-1.3.1.dist-info/RECORD
