Metadata-Version: 2.1
Name: up-symk
Version: 1.3.1
Summary: Unified Planning Integration of the SymK planner
Home-page: https://github.com/aiplan4eu/symk/
Author: David Speck
Author-email: david.speck@liu.se
License: UNKNOWN
Platform: UNKNOWN
Classifier: Development Status :: 4 - Beta
Classifier: License :: OSI Approved :: GNU General Public License v3 (GPLv3)
Classifier: Programming Language :: Python :: 3
Classifier: Topic :: Scientific/Engineering :: Artificial Intelligence
License-File: LICENSE.md
